pystalk/__init__.py
pystalk/client.py
pystalk/pool.py
pystalk-0.7.0.dist-info/LICENSE.txt
pystalk-0.7.0.dist-info/METADATA
pystalk-0.7.0.dist-info/WHEEL
pystalk-0.7.0.dist-info/top_level.txt
pystalk-0.7.0.dist-info/RECORD
