Metadata-Version: 2.1
Name: pystalk
Version: 0.7.0
Summary: Very simple beanstalkd client
Home-page: https://github.com/easypost/pystalk
Author: EasyPost
Author-email: oss@easypost.com
License: ISC
Project-URL: CI, https://travis-ci.com/EasyPost/pystalk
Classifier: Development Status :: 4 - Beta
Classifier: Environment :: Console
Classifier: Programming Language :: Python
Classifier: Programming Language :: Python :: 3.6
Classifier: Programming Language :: Python :: 3.7
Classifier: Programming Language :: Python :: 3.8
Classifier: Programming Language :: Python :: 3.9
Classifier: Programming Language :: Python :: 3.10
Classifier: Intended Audience :: System Administrators
Classifier: Operating System :: OS Independent
Classifier: Topic :: Database
Classifier: License :: OSI Approved :: ISC License (ISCL)
Requires-Python: >=3.6, <4
License-File: LICENSE.txt
Requires-Dist: PyYAML (>=3.0)
Requires-Dist: attrs (>=19.2)
Requires-Dist: six
